<?xml version="1.0"?>
<!DOCTYPE hibernate-mapping PUBLIC "-//Hibernate/Hibernate Mapping DTD 3.0//EN"
"http://www.hibernate.org/dtd/hibernate-mapping-3.0.dtd">
<!-- Generated 13-05-2014 07:57:07 PM by Hibernate Tools 3.6.0 -->
<hibernate-mapping>
    <class name="cl.movistar.hibernate.dto.EventoSistema" table="evento_sistema" catalog="USERTRCK">
        <id name="id" type="int">
            <column name="id" />
            <generator class="assigned" />
        </id>
        <property name="nombre" type="string">
            <column name="nombre" length="100" not-null="true" />
        </property>
        <property name="descripcion" type="string">
            <column name="descripcion" length="100" not-null="true" />
        </property>
        <property name="accionesSistema" type="string">
            <column name="acciones_sistema" length="100" not-null="true" />
        </property>
    </class>
</hibernate-mapping>
